README.md
setup.cfg
setup.py
package1/__init__.py
package1/module1.py
package2/__init__.py
package2/module2.py
super_crawler.egg-info/PKG-INFO
super_crawler.egg-info/SOURCES.txt
super_crawler.egg-info/dependency_links.txt
super_crawler.egg-info/top_level.txt