Metadata-Version: 1.1
Name: super-crawler
Version: 0.1.0
Summary: 第一個上架套件
Home-page: https://github.com/telliex/pip_project_1.git
Author: telliex
Author-email: telliexyuzo@gmail.com
License: UNKNOWN
Download-URL: https://github.com/telliex/pip_project_1/archive/v0.1.0.zip
Keywords: crawler
Platform: UNKNOWN
Classifier: License :: OSI Approved :: MIT License
Classifier: Programming Language :: Python
Classifier: Intended Audience :: Developers
Classifier: Operating System :: OS Independent
